tiniyo/__init__.py
tiniyo/rest/__init__.py
tiniyo-1.0.2.dist-info/METADATA
tiniyo-1.0.2.dist-info/WHEEL
tiniyo-1.0.2.dist-info/top_level.txt
tiniyo-1.0.2.dist-info/RECORD
